selfcaffeinate/__about__.py
selfcaffeinate/__init__.py
selfcaffeinate/selfcaffeinate.py
selfcaffeinate/version.py
selfcaffeinate/config/default.yaml
selfcaffeinate-0.1.0.dist-info/LICENSE
selfcaffeinate-0.1.0.dist-info/METADATA
selfcaffeinate-0.1.0.dist-info/WHEEL
selfcaffeinate-0.1.0.dist-info/top_level.txt
selfcaffeinate-0.1.0.dist-info/RECORD
