Metadata-Version: 2.1
Name: selfcaffeinate
Version: 0.1.0
Summary: Python module to prevent macOS system sleep using the caffeinate(1) command
Home-page: https://github.com/zcutlip/py-self-caffeinate
Author: Zachary Cutlip
Author-email: uid000@gmail.com
License: MIT
Platform: darwin
Requires-Python: >=3.7
License-File: LICENSE
